[
  {
    "file": ".anchor"
  },
  {
    "file": ".gitattributes"
  },
  {
    "file": "README.md"
  },
  {
    "file": "SOVEREIGN-ENVIRONMENT.md"
  },
  {
    "file": "SPEC.md"
  },
  {
    "file": "TRUTH.md"
  },
  {
    "file": "bin/gate.mjs"
  },
  {
    "file": "bin/heartbeat.mjs"
  },
  {
    "file": "bin/run-vectors.cjs"
  },
  {
    "file": "constitution.snapshot.json.asc"
  },
  {
    "file": "gate.mjs"
  },
  {
    "file": "heartbeat.mjs"
  },
  {
    "file": "run-vectors.cjs"
  },
  {
    "file": "swarm_anchor.txt"
  }
]